conf_eval/__init__.py
conf_eval/_utils.py
conf_eval/cpsign/__init__.py
conf_eval/cpsign/_load.py
conf_eval/cpsign/report/__init__.py
conf_eval/cpsign/report/_html.py
conf_eval/cpsign/report/_static/UU_logo.svg
conf_eval/cpsign/report/_static/arosbio-logo.png
conf_eval/cpsign/report/_static/pharmbio-logo-new.png
conf_eval/cpsign/report/_static/style.css
conf_eval/cpsign/report/_templates/cp_metrics_template.html
conf_eval/cpsign/report/_templates/template.html
conf_eval/cpsign/report/_templates/vap_metrics_template.html
conf_eval/cpsign/report/html.py
conf_eval/metrics/__init__.py
conf_eval/metrics/_classification.py
conf_eval/metrics/_regression.py
conf_eval/plot/__init__.py
conf_eval/plot/_classification.py
conf_eval/plot/_common.py
conf_eval/plot/_regression.py
conf_eval/plot/_utils.py
conformal_eval-1.0.0b3.dist-info/LICENSE.txt
conformal_eval-1.0.0b3.dist-info/METADATA
conformal_eval-1.0.0b3.dist-info/WHEEL
conformal_eval-1.0.0b3.dist-info/entry_points.txt
conformal_eval-1.0.0b3.dist-info/RECORD
