Metadata-Version: 2.1
Name: conformal-eval
Version: 1.0.0b3
Summary: A package with utility functions for evaluating conformal predictors
Home-page: https://github.com/pharmbio/conformal-eval
License: MIT
Author: Staffan Arvidsson McShane
Author-email: staffan.arvidsson@gmail.com
Requires-Python: >=3.8,<4.0
Classifier: License :: OSI Approved :: MIT License
Classifier: Operating System :: OS Independent
Classifier: Programming Language :: Python :: 3
Classifier: Programming Language :: Python :: 3.8
Classifier: Programming Language :: Python :: 3.9
Classifier: Programming Language :: Python :: 3.10
Classifier: Programming Language :: Python :: 3.11
Classifier: Programming Language :: Python :: 3.12
Provides-Extra: report
Requires-Dist: Jinja2 (>=3.0,<4.0) ; extra == "report"
Requires-Dist: matplotlib (>=3.4,<4.0)
Requires-Dist: numpy (>=1.19,<2.0)
Requires-Dist: pandas (>=2.0,<3.0)
Requires-Dist: scikit-learn (>=1.0.0,<2.0.0)
Requires-Dist: seaborn (>=0.12,<0.13)
Project-URL: Repository, https://github.com/pharmbio/conformal-eval
